[
  {
    "tag_name": "entity",
    "ids_to_tags": {
      "1": "B-Autonomia_Territorial",
      "2": "I-Autonomia_Territorial",
      "3": "L-Autonomia_Territorial",
      "4": "U-Autonomia_Territorial",
      "5": "B-Autoridad_Propia",
      "6": "I-Autoridad_Propia",
      "7": "L-Autoridad_Propia",
      "8": "U-Autoridad_Propia",
      "9": "B-Cabildo_Abierto",
      "10": "I-Cabildo_Abierto",
      "11": "L-Cabildo_Abierto",
      "12": "U-Cabildo_Abierto",
      "13": "B-Caminos_Resistencia",
      "14": "I-Caminos_Resistencia",
      "15": "L-Caminos_Resistencia",
      "16": "U-Caminos_Resistencia",
      "17": "B-Conflicto_Armado",
      "18": "I-Conflicto_Armado",
      "19": "L-Conflicto_Armado",
      "20": "U-Conflicto_Armado",
      "21": "B-Convivencia_Armonica",
      "22": "I-Convivencia_Armonica",
      "23": "L-Convivencia_Armonica",
      "24": "U-Convivencia_Armonica",
      "25": "B-Cultura_Autonomia",
      "26": "I-Cultura_Autonomia",
      "27": "L-Cultura_Autonomia",
      "28": "U-Cultura_Autonomia",
      "29": "B-Defensa_Territorio",
      "30": "I-Defensa_Territorio",
      "31": "L-Defensa_Territorio",
      "32": "U-Defensa_Territorio",
      "33": "B-Derecho_Territorial",
      "34": "I-Derecho_Territorial",
      "35": "L-Derecho_Territorial",
      "36": "U-Derecho_Territorial",
      "37": "B-Desplazamiento",
      "38": "I-Desplazamiento",
      "39": "L-Desplazamiento",
      "40": "U-Desplazamiento",
      "41": "B-Dignidad_Humana",
      "42": "I-Dignidad_Humana",
      "43": "L-Dignidad_Humana",
      "44": "U-Dignidad_Humana",
      "45": "B-Diversidad_Etnica_Cultural",
      "46": "I-Diversidad_Etnica_Cultural",
      "47": "L-Diversidad_Etnica_Cultural",
      "48": "U-Diversidad_Etnica_Cultural",
      "49": "B-Espiritualidad_Nasa",
      "50": "I-Espiritualidad_Nasa",
      "51": "L-Espiritualidad_Nasa",
      "52": "U-Espiritualidad_Nasa",
      "53": "B-Estados",
      "54": "I-Estados",
      "55": "L-Estados",
      "56": "U-Estados",
      "57": "B-Gobierno_Propio",
      "58": "I-Gobierno_Propio",
      "59": "L-Gobierno_Propio",
      "60": "U-Gobierno_Propio",
      "61": "B-Memoria_Historica",
      "62": "I-Memoria_Historica",
      "63": "L-Memoria_Historica",
      "64": "U-Memoria_Historica",
      "65": "B-Participacion_Comunitaria",
      "66": "I-Participacion_Comunitaria",
      "67": "L-Participacion_Comunitaria",
      "68": "U-Participacion_Comunitaria",
      "69": "B-Recuperacion_Tierras_Resguardo",
      "70": "I-Recuperacion_Tierras_Resguardo",
      "71": "L-Recuperacion_Tierras_Resguardo",
      "72": "U-Recuperacion_Tierras_Resguardo",
      "73": "B-Resistencia_Pacifica",
      "74": "I-Resistencia_Pacifica",
      "75": "L-Resistencia_Pacifica",
      "76": "U-Resistencia_Pacifica",
      "77": "B-Resistencia_Unidad",
      "78": "I-Resistencia_Unidad",
      "79": "L-Resistencia_Unidad",
      "80": "U-Resistencia_Unidad",
      "81": "B-Territorio_Madre_Tierra",
      "82": "I-Territorio_Madre_Tierra",
      "83": "L-Territorio_Madre_Tierra",
      "84": "U-Territorio_Madre_Tierra",
      "0": "O"
    },
    "tags_to_ids": {
      "B-Autonomia_Territorial": 1,
      "I-Autonomia_Territorial": 2,
      "L-Autonomia_Territorial": 3,
      "U-Autonomia_Territorial": 4,
      "B-Autoridad_Propia": 5,
      "I-Autoridad_Propia": 6,
      "L-Autoridad_Propia": 7,
      "U-Autoridad_Propia": 8,
      "B-Cabildo_Abierto": 9,
      "I-Cabildo_Abierto": 10,
      "L-Cabildo_Abierto": 11,
      "U-Cabildo_Abierto": 12,
      "B-Caminos_Resistencia": 13,
      "I-Caminos_Resistencia": 14,
      "L-Caminos_Resistencia": 15,
      "U-Caminos_Resistencia": 16,
      "B-Conflicto_Armado": 17,
      "I-Conflicto_Armado": 18,
      "L-Conflicto_Armado": 19,
      "U-Conflicto_Armado": 20,
      "B-Convivencia_Armonica": 21,
      "I-Convivencia_Armonica": 22,
      "L-Convivencia_Armonica": 23,
      "U-Convivencia_Armonica": 24,
      "B-Cultura_Autonomia": 25,
      "I-Cultura_Autonomia": 26,
      "L-Cultura_Autonomia": 27,
      "U-Cultura_Autonomia": 28,
      "B-Defensa_Territorio": 29,
      "I-Defensa_Territorio": 30,
      "L-Defensa_Territorio": 31,
      "U-Defensa_Territorio": 32,
      "B-Derecho_Territorial": 33,
      "I-Derecho_Territorial": 34,
      "L-Derecho_Territorial": 35,
      "U-Derecho_Territorial": 36,
      "B-Desplazamiento": 37,
      "I-Desplazamiento": 38,
      "L-Desplazamiento": 39,
      "U-Desplazamiento": 40,
      "B-Dignidad_Humana": 41,
      "I-Dignidad_Humana": 42,
      "L-Dignidad_Humana": 43,
      "U-Dignidad_Humana": 44,
      "B-Diversidad_Etnica_Cultural": 45,
      "I-Diversidad_Etnica_Cultural": 46,
      "L-Diversidad_Etnica_Cultural": 47,
      "U-Diversidad_Etnica_Cultural": 48,
      "B-Espiritualidad_Nasa": 49,
      "I-Espiritualidad_Nasa": 50,
      "L-Espiritualidad_Nasa": 51,
      "U-Espiritualidad_Nasa": 52,
      "B-Estados": 53,
      "I-Estados": 54,
      "L-Estados": 55,
      "U-Estados": 56,
      "B-Gobierno_Propio": 57,
      "I-Gobierno_Propio": 58,
      "L-Gobierno_Propio": 59,
      "U-Gobierno_Propio": 60,
      "B-Memoria_Historica": 61,
      "I-Memoria_Historica": 62,
      "L-Memoria_Historica": 63,
      "U-Memoria_Historica": 64,
      "B-Participacion_Comunitaria": 65,
      "I-Participacion_Comunitaria": 66,
      "L-Participacion_Comunitaria": 67,
      "U-Participacion_Comunitaria": 68,
      "B-Recuperacion_Tierras_Resguardo": 69,
      "I-Recuperacion_Tierras_Resguardo": 70,
      "L-Recuperacion_Tierras_Resguardo": 71,
      "U-Recuperacion_Tierras_Resguardo": 72,
      "B-Resistencia_Pacifica": 73,
      "I-Resistencia_Pacifica": 74,
      "L-Resistencia_Pacifica": 75,
      "U-Resistencia_Pacifica": 76,
      "B-Resistencia_Unidad": 77,
      "I-Resistencia_Unidad": 78,
      "L-Resistencia_Unidad": 79,
      "U-Resistencia_Unidad": 80,
      "B-Territorio_Madre_Tierra": 81,
      "I-Territorio_Madre_Tierra": 82,
      "L-Territorio_Madre_Tierra": 83,
      "U-Territorio_Madre_Tierra": 84,
      "O": 0
    },
    "num_tags": 85
  }
]